hddtempnc/__init__.py
hddtempnc/hddtempnc.py
hddtempnc-1.3.0.dist-info/METADATA
hddtempnc-1.3.0.dist-info/RECORD
hddtempnc-1.3.0.dist-info/WHEEL
hddtempnc-1.3.0.dist-info/top_level.txt
