Metadata-Version: 2.1
Name: hddtempnc
Version: 1.3.0
Summary: Tool to acquire hard disk drive temperature from the network interface
Home-page: https://github.com/viharm/HDDtempNC
Author: Viharm
Author-email: viharm@malviya.net
License: UNKNOWN
Project-URL: Bug Reports, https://github.com/viharm/HDDtempNC/issues
Project-URL: Source, https://github.com/viharm/HDDtempNC
Keywords: python hddtemp netcat terminal hdd
Platform: UNKNOWN
Classifier: Programming Language :: Python
Classifier: License :: Other/Proprietary License
Classifier: Operating System :: OS Independent
Classifier: Development Status :: 5 - Production/Stable
Classifier: Environment :: Console
Classifier: Intended Audience :: Developers
Classifier: Intended Audience :: End Users/Desktop
Classifier: Natural Language :: English
Classifier: Topic :: System :: Hardware
Classifier: Topic :: System :: Monitoring
Classifier: Topic :: Terminals
Classifier: Topic :: Utilities
